trains/trains.py
trains/static/London Underground Bold.ttf
trains/static/London Underground Heavy.ttf
trains/static/London Underground Medium.ttf
trains/static/London Underground Regular.ttf
trains/templates/home.html
next_trains-0.2.0.dist-info/METADATA
next_trains-0.2.0.dist-info/WHEEL
next_trains-0.2.0.dist-info/entry_points.txt
next_trains-0.2.0.dist-info/licenses/LICENSE
next_trains-0.2.0.dist-info/licenses/vendor/api-licence.pdf
next_trains-0.2.0.dist-info/RECORD
