Metadata-Version: 2.4
Name: next-trains
Version: 0.2.0
Summary: An imagining of a combined Arrivals and Departure board.
Project-URL: Homepage, https://codeberg.org/MikeCoats/next-trains
Project-URL: Repository, https://codeberg.org/MikeCoats/next-trains.git
Project-URL: Issues, https://codeberg.org/MikeCoats/next-trains/issues
Author-email: Mike Coats <i.am@mikecoats.com>
License-Expression: AGPL-3.0-or-later
License-File: LICENSE
License-File: vendor/api-licence.pdf
Keywords: api,arrival,departure,flask,rail,railway,station,trains,uk,web
Classifier: Development Status :: 3 - Alpha
Classifier: Environment :: Web Environment
Classifier: Framework :: Flask
Classifier: Intended Audience :: End Users/Desktop
Classifier: License :: OSI Approved :: GNU Affero General Public License v3 or later (AGPLv3+)
Classifier: Natural Language :: English
Classifier: Programming Language :: Python :: 3
Classifier: Programming Language :: Python :: 3.11
Classifier: Topic :: Internet :: WWW/HTTP :: Dynamic Content
Classifier: Topic :: Internet :: WWW/HTTP :: WSGI :: Application
Requires-Python: >=3.11
Requires-Dist: arrow~=1.3.0
Requires-Dist: asgiref~=3.8.1
Requires-Dist: flask~=3.1.0
Requires-Dist: python-dotenv~=1.0.1
Requires-Dist: requests~=2.32.3
Requires-Dist: uvicorn~=0.34.0
Provides-Extra: dev
Requires-Dist: black~=24.10.0; extra == 'dev'
Requires-Dist: build~=1.2.2; extra == 'dev'
Requires-Dist: flake8-pyproject~=1.2.3; extra == 'dev'
Requires-Dist: flake8~=7.1.1; extra == 'dev'
Requires-Dist: isort~=5.13.2; extra == 'dev'
Requires-Dist: pylint~=3.3.3; extra == 'dev'
Requires-Dist: twine~=6.1.0; extra == 'dev'
